odoo10_addon_account_bank_reconcile_hook-10.0.1.0.0.99.dev1-nspkg.pth
odoo/addons/account_bank_reconcile_hook/README.rst
odoo/addons/account_bank_reconcile_hook/__init__.py
odoo/addons/account_bank_reconcile_hook/__manifest__.py
odoo/addons/account_bank_reconcile_hook/i18n/account_bank_reconcile_hook.pot
odoo/addons/account_bank_reconcile_hook/models/__init__.py
odoo/addons/account_bank_reconcile_hook/models/account_bank_statement_line.py
odoo/addons/account_bank_reconcile_hook/static/description/icon.png
odoo10_addon_account_bank_reconcile_hook-10.0.1.0.0.99.dev1.dist-info/METADATA
odoo10_addon_account_bank_reconcile_hook-10.0.1.0.0.99.dev1.dist-info/WHEEL
odoo10_addon_account_bank_reconcile_hook-10.0.1.0.0.99.dev1.dist-info/namespace_packages.txt
odoo10_addon_account_bank_reconcile_hook-10.0.1.0.0.99.dev1.dist-info/top_level.txt
odoo10_addon_account_bank_reconcile_hook-10.0.1.0.0.99.dev1.dist-info/RECORD
