Metadata-Version: 2.1
Name: odoo10-addon-account-bank-reconcile-hook
Version: 10.0.1.0.0.99.dev1
Summary: Bank Reconciliation Threshold
Home-page: https://github.com/OCA/account-reconcile
Author: Odoo SA,Odoo Community Association (OCA)
Author-email: support@odoo-community.org
License: LGPL-3
Platform: UNKNOWN
Classifier: Programming Language :: Python
Classifier: Framework :: Odoo
Classifier: License :: OSI Approved :: GNU Lesser General Public License v3 (LGPLv3)
Requires-Python: ~=2.7
Requires-Dist: odoo (<10.1dev,>=10.0)
